flask_Captchaify/__init__.py
flask_Captchaify/altcha.py
flask_Captchaify/cryptograph.py
flask_Captchaify/embed.py
flask_Captchaify/req_info.py
flask_Captchaify/trueclick.py
flask_Captchaify/utils.py
flask_Captchaify/webtoolbox.py
flask_Captchaify/assets/Comic_Sans_MS.ttf
flask_Captchaify/assets/DroidSansMono.ttf
flask_Captchaify/assets/GeoLite2-ASN.mmdb
flask_Captchaify/assets/GeoLite2-City.mmdb
flask_Captchaify/assets/Helvetica.ttf
flask_Captchaify/assets/emojis.json
flask_Captchaify/assets/languages.json
flask_Captchaify/assets/tea_emojis.json
flask_Captchaify/assets/trueclick-min.js
flask_Captchaify/templates/blocked.html
flask_Captchaify/templates/captcha_clickable.html
flask_Captchaify/templates/captcha_multiclick.html
flask_Captchaify/templates/captcha_oneclick.html
flask_Captchaify/templates/captcha_text_audio.html
flask_Captchaify/templates/captcha_third_party.html
flask_Captchaify/templates/change_language.html
flask_Captchaify/templates/exception.html
flask_Captchaify/templates/nojs.html
flask_Captchaify/templates/rate_limited.html
flask_Captchaify/templates/assets/colors.j2
flask_Captchaify/templates/assets/cookie_banner_css.j2
flask_Captchaify/templates/assets/cookie_banner_html.j2
flask_Captchaify/templates/assets/cookie_banner_js.j2
flask_Captchaify/templates/assets/footer_css.j2
flask_Captchaify/templates/assets/footer_html.j2
flask_captchaify-1.8.5.dist-info/licenses/LICENSE
flask_captchaify-1.8.5.dist-info/METADATA
flask_captchaify-1.8.5.dist-info/WHEEL
flask_captchaify-1.8.5.dist-info/top_level.txt
flask_captchaify-1.8.5.dist-info/RECORD
