Metadata-Version: 2.4
Name: flask_Captchaify
Version: 1.8.5
Summary: Protect against bots and DDoS attacks
Home-page: https://github.com/tn3w/flask_Captchaify
Author: TN3W
Author-email: tn3wA8xxfuVMs2@proton.me
License: GPL-3.0
Keywords: flask,Python,Bot,Captcha,DDoS,robot,crawler,rate-limiting,bot-protection
Classifier: Environment :: Web Environment
Classifier: Development Status :: 5 - Production/Stable
Classifier: Intended Audience :: Developers
Classifier: License :: OSI Approved :: GNU General Public License v3 (GPLv3)
Classifier: Programming Language :: Python
Classifier: Programming Language :: Python :: 3
Classifier: Topic :: Internet :: WWW/HTTP :: Dynamic Content
Classifier: Topic :: Software Development :: Libraries :: Python Modules
License-File: LICENSE
Requires-Dist: cryptography
Requires-Dist: aiohttp>=3.9.5
Requires-Dist: urllib3>=2.2.2
Requires-Dist: Flask
Requires-Dist: Jinja2
Requires-Dist: werkzeug>=3.0.1
Requires-Dist: aiohttp>=3.9.4
Requires-Dist: googletrans==3.1.0a0
Requires-Dist: beautifulsoup4
Requires-Dist: bs4
Requires-Dist: crawler-user-agents
Requires-Dist: opencv-python
Requires-Dist: numpy>=2.0.0
Requires-Dist: dnspython>=2.6.1
Requires-Dist: geoip2>=4.8.0
Requires-Dist: captcha
Dynamic: author
Dynamic: author-email
Dynamic: classifier
Dynamic: description
Dynamic: description-content-type
Dynamic: home-page
Dynamic: keywords
Dynamic: license
Dynamic: license-file
Dynamic: requires-dist
Dynamic: summary
